LICENSE
MANIFEST.in
README.md
setup.cfg
setup.py
aiocryptocurrency/__init__.py
aiocryptocurrency.egg-info/PKG-INFO
aiocryptocurrency.egg-info/SOURCES.txt
aiocryptocurrency.egg-info/dependency_links.txt
aiocryptocurrency.egg-info/not-zip-safe
aiocryptocurrency.egg-info/requires.txt
aiocryptocurrency.egg-info/top_level.txt
aiocryptocurrency/coins/__init__.py
aiocryptocurrency/coins/firo.py
aiocryptocurrency/coins/nero.py