Metadata-Version: 2.1
Name: aiocryptocurrency
Version: 0.1.1
Summary: Abstraction library for managing funds for various cryptocurrencies via their RPCs
Home-page: https://github.com/sanderfoobar/aiocryptocurrency
Author: Sander
Author-email: sander@sanderf.nl
License: UNKNOWN
Keywords: cryptocurrency
Platform: any
Classifier: Environment :: Web Environment
Classifier: Intended Audience :: Developers
Classifier: Operating System :: OS Independent
Classifier: Programming Language :: Python :: 3
Classifier: Programming Language :: Python :: 3.7
Classifier: Programming Language :: Python :: 3.8
Classifier: License :: OSI Approved :: BSD License
Classifier: Topic :: Internet :: WWW/HTTP :: Dynamic Content
Classifier: Topic :: Software Development :: Libraries :: Python Modules
Requires-Python: >=3.6
License-File: LICENSE
